Workbook
Name expense: 'Pivot Tables'!$C$20
Name month: Dashboard!$C$5
Name revenue: 'Pivot Tables'!$C$21
Name Slicer_Financial_Type: #N/A
Name Slicer_Month: #N/A
Name Slicer_Region: #N/A

Sheet Dashboard with slicers

Sheet Dashboard
B2: Budget vs. Actual Dashboard
B3: Fiscal Year -> | C3: 2025
B5: Current Month -> | C5: February
B7: Figures in USD | C7: Budget | D7: Actual | F7: Var. Abs. | G7: Var. % | I7: Income: Budget vs Actuals Income | P7: Expenses: Actuals Income
B8: Income:
B9: Product Revenue | C9: =SUMIFS('Clean Ledger Data'!F:F,'Clean Ledger Data'!D:D,Dashboard!B9,'Clean Ledger Data'!B:B,Dashboard!$C$5) -> 443559 | D9: =SUMIFS('Clean Ledger Data'!G:G,'Clean Ledger Data'!D:D,Dashboard!B9,'Clean Ledger Data'!B:B,Dashboard!$C$5) -> 459069 | F9: =D9-C9 -> 15510 | G9: =D9/C9-1 -> 0.034967163
B10: Service Revenue | C10: =SUMIFS('Clean Ledger Data'!F:F,'Clean Ledger Data'!D:D,Dashboard!B10,'Clean Ledger Data'!B:B,Dashboard!$C$5) -> 127713 | D10: =SUMIFS('Clean Ledger Data'!G:G,'Clean Ledger Data'!D:D,Dashboard!B10,'Clean Ledger Data'!B:B,Dashboard!$C$5) -> 125945 | F10: =D10-C10 -> -1768 | G10: =D10/C10-1 -> -0.01384354
B11: Total Revenue | C11: =SUM(C9:C10) -> 571272 | D11: =SUM(D9:D10) -> 585014 | F11: =D11-C11 -> 13742 | G11: =D11/C11-1 -> 0.024055091
B13: Expenses:
B14: Travel | C14: =SUMIFS('Clean Ledger Data'!F:F,'Clean Ledger Data'!D:D,Dashboard!B14,'Clean Ledger Data'!B:B,Dashboard!$C$5) -> 12668 | D14: =SUMIFS('Clean Ledger Data'!G:G,'Clean Ledger Data'!D:D,Dashboard!B14,'Clean Ledger Data'!B:B,Dashboard!$C$5) -> 13113 | F14: =C14-D14 -> -445 | G14: =C14/D14-1 -> -0.033935789
B15: Infrastructure | C15: =SUMIFS('Clean Ledger Data'!F:F,'Clean Ledger Data'!D:D,Dashboard!B15,'Clean Ledger Data'!B:B,Dashboard!$C$5) -> 76115 | D15: =SUMIFS('Clean Ledger Data'!G:G,'Clean Ledger Data'!D:D,Dashboard!B15,'Clean Ledger Data'!B:B,Dashboard!$C$5) -> 78894 | F15: =C15-D15 -> -2779 | G15: =C15/D15-1 -> -0.035224478
B16: Salaries | C16: =SUMIFS('Clean Ledger Data'!F:F,'Clean Ledger Data'!D:D,Dashboard!B16,'Clean Ledger Data'!B:B,Dashboard!$C$5) -> 324477 | D16: =SUMIFS('Clean Ledger Data'!G:G,'Clean Ledger Data'!D:D,Dashboard!B16,'Clean Ledger Data'!B:B,Dashboard!$C$5) -> 326577 | F16: =C16-D16 -> -2100 | G16: =C16/D16-1 -> -0.0064303365
B17: Utilities | C17: =SUMIFS('Clean Ledger Data'!F:F,'Clean Ledger Data'!D:D,Dashboard!B17,'Clean Ledger Data'!B:B,Dashboard!$C$5) -> 23679 | D17: =SUMIFS('Clean Ledger Data'!G:G,'Clean Ledger Data'!D:D,Dashboard!B17,'Clean Ledger Data'!B:B,Dashboard!$C$5) -> 22137 | F17: =C17-D17 -> 1542 | G17: =C17/D17-1 -> 0.069657135
B18: Marketing Spend | C18: =SUMIFS('Clean Ledger Data'!F:F,'Clean Ledger Data'!D:D,Dashboard!B18,'Clean Ledger Data'!B:B,Dashboard!$C$5) -> 40954 | D18: =SUMIFS('Clean Ledger Data'!G:G,'Clean Ledger Data'!D:D,Dashboard!B18,'Clean Ledger Data'!B:B,Dashboard!$C$5) -> 43825 | F18: =C18-D18 -> -2871 | G18: =C18/D18-1 -> -0.065510553
B19: Training | C19: =SUMIFS('Clean Ledger Data'!F:F,'Clean Ledger Data'!D:D,Dashboard!B19,'Clean Ledger Data'!B:B,Dashboard!$C$5) -> 13797 | D19: =SUMIFS('Clean Ledger Data'!G:G,'Clean Ledger Data'!D:D,Dashboard!B19,'Clean Ledger Data'!B:B,Dashboard!$C$5) -> 15353 | F19: =C19-D19 -> -1556 | G19: =C19/D19-1 -> -0.10134827
B20: Total Expenses | C20: =SUM(C14:C19) -> 491690 | D20: =SUM(D14:D19) -> 499899 | F20: =C20-D20 -> -8209 | G20: =C20/D20-1 -> -0.016421317
B22: Savings | C22: =C11-C20 -> 79582 | D22: =D11-D20 -> 85115 | F22: =C22-D22 -> -5533 | G22: =C22/D22-1 -> -0.065006168

Sheet Pivot Tables
A1: Financial Type | B1: Expense
A3: Budget | B3: Column Labels
A4: Row Labels | B4: February | C4: Grand Total
A5: Infrastructure | B5: 76115 | C5: 76115
A6: Marketing Spend | B6: 40954 | C6: 40954
A7: Salaries | B7: 324477 | C7: 324477
A8: Training | B8: 13797 | C8: 13797
A9: Travel | B9: 12668 | C9: 12668
A10: Utilities | B10: 23679 | C10: 23679
A11: Grand Total | B11: 491690 | C11: 491690
J16: Financial Type | K16: Expense
A18: Row Labels | B18: Budget | C18: Actual | E18: Row Labels | F18: Budget | G18: Actual | J18: Sum of Actual Amount | K18: Column Labels
A19: February | B19: 491690 | C19: 499899 | E19: Central | F19: 141534 | G19: 145195 | J19: Row Labels | K19: January | L19: February | M19: March | N19: April | O19: May | P19: June | Q19: July | R19: August | S19: September | T19: October | U19: November | V19: December | W19: Grand Total
A20: Expense | B20: 491690 | C20: 499899 | E20: Expense | F20: 141534 | G20: 145195 | J20: Infrastructure | K20: 58614 | L20: 78894 | M20: 23607 | N20: 20286 | O20: 44297 | P20: 39120 | Q20: 47588 | R20: 22481 | S20: 36050 | T20: 38017 | U20: 45468 | V20: 51898 | W20: 506320
A21: Grand Total | B21: 491690 | C21: 499899 | E21: East | F21: 23679 | G21: 22137 | J21: Marketing Spend | K21: 25367 | L21: 43825 | M21: 18659 | N21: 50017 | O21: 73134 | P21: 29840 | Q21: 17966 | R21: 51999 | S21: 21254 | T21: 68632 | U21: 18718 | V21: 63971 | W21: 483382
E22: Expense | F22: 23679 | G22: 22137 | J22: Salaries | K22: 304544 | L22: 326577 | M22: 309825 | N22: 305777 | O22: 319171 | P22: 302755 | Q22: 319768 | R22: 333927 | S22: 303170 | T22: 335955 | U22: 322846 | V22: 334451 | W22: 3818766
E23: North | F23: 107977 | G23: 109264 | J23: Training | K23: 19889 | L23: 15353 | M23: 8839 | O23: 5987 | Q23: 8007 | S23: 9124 | U23: 11318 | V23: 15748 | W23: 94265
E24: Expense | F24: 107977 | G24: 109264 | J24: Travel | K24: 17138 | L24: 13113 | M24: 18428 | N24: 5149 | O24: 8422 | P24: 11913 | Q24: 20892 | R24: 18446 | S24: 10287 | T24: 13130 | U24: 7254 | V24: 18215 | W24: 162387
E25: South | F25: 122509 | G25: 125754 | J25: Utilities | K25: 40864 | L25: 22137 | M25: 78036 | N25: 20481 | O25: 40730 | P25: 16800 | Q25: 25000 | R25: 23519 | S25: 40922 | T25: 53451 | U25: 82370 | V25: 40025 | W25: 484335
E26: Expense | F26: 122509 | G26: 125754 | J26: Grand Total | K26: 466416 | L26: 499899 | M26: 457394 | N26: 401710 | O26: 491741 | P26: 400428 | Q26: 439221 | R26: 450372 | S26: 420807 | T26: 509185 | U26: 487974 | V26: 524308 | W26: 5549455
E27: West | F27: 95991 | G27: 97549
E28: Expense | F28: 95991 | G28: 97549
E29: Grand Total | F29: 491690 | G29: 499899

Sheet Clean Ledger Data
A1: Date | B1: Month | C1: Department | D1: Category | E1: Region | F1: Budget Amount | G1: Actual Amount | H1: Payment Method | I1: Transaction ID | J1: Financial Type | L1: category | M1: financial type
A2: 2025-01-25 00:00:00 | B2: =TEXT(A2,"mmmm") -> January | C2: Operations | D2: Salaries | E2: South | F2: 55476 | G2: 54613 | H2: Bank Transfer | I2: TXN100001 | J2: Expense | L2: {=_xlfn.UNIQUE(D2:D202)} -> Salaries | M2: Expense
A3: 2025-01-25 00:00:00 | B3: =TEXT(A3,"mmmm") -> January | C3: Finance | D3: Salaries | E3: Central | F3: 49012 | G3: 48469 | H3: Bank Transfer | I3: TXN100002 | J3: Expense | L3: Utilities | M3: Expense
A4: 2025-01-25 00:00:00 | B4: =TEXT(A4,"mmmm") -> January | C4: Marketing | D4: Salaries | E4: East | F4: 56087 | G4: 56626 | H4: Bank Transfer | I4: TXN100003 | J4: Expense | L4: Infrastructure | M4: Expense
A5: 2025-01-25 00:00:00 | B5: =TEXT(A5,"mmmm") -> January | C5: IT | D5: Salaries | E5: Central | F5: 46424 | G5: 46592 | H5: Bank Transfer | I5: TXN100004 | J5: Expense | L5: Marketing Spend | M5: Expense
A6: 2025-01-25 00:00:00 | B6: =TEXT(A6,"mmmm") -> January | C6: HR | D6: Salaries | E6: West | F6: 45488 | G6: 44748 | H6: Bank Transfer | I6: TXN100005 | J6: Expense | L6: Travel | M6: Expense
A7: 2025-01-25 00:00:00 | B7: =TEXT(A7,"mmmm") -> January | C7: Sales | D7: Salaries | E7: East | F7: 53279 | G7: 53496 | H7: Bank Transfer | I7: TXN100006 | J7: Expense | L7: Training | M7: Expense
A8: 2025-01-10 00:00:00 | B8: =TEXT(A8,"mmmm") -> January | C8: HR | D8: Utilities | E8: North | F8: 38462 | G8: 40864 | H8: Card | I8: TXN100007 | J8: Expense | L8: Product Revenue | M8: Income
A9: 2025-01-10 00:00:00 | B9: =TEXT(A9,"mmmm") -> January | C9: Operations | D9: Infrastructure | E9: West | F9: 34309 | G9: 33264 | H9: Cash | I9: TXN100008 | J9: Expense | L9: Service Revenue | M9: Income
A10: 2025-01-10 00:00:00 | B10: =TEXT(A10,"mmmm") -> January | C10: Finance | D10: Infrastructure | E10: South | F10: 26149 | G10: 25350 | H10: Bank Transfer | I10: TXN100009 | J10: Expense
A11: 2025-01-10 00:00:00 | B11: =TEXT(A11,"mmmm") -> January | C11: Marketing | D11: Marketing Spend | E11: East | F11: 27449 | G11: 25367 | H11: UPI | I11: TXN100010 | J11: Expense
A12: 2025-01-15 00:00:00 | B12: =TEXT(A12,"mmmm") -> January | C12: Operations | D12: Travel | E12: North | F12: 16955 | G12: 17138 | H12: Bank Transfer | I12: TXN100011 | J12: Expense
A13: 2025-01-15 00:00:00 | B13: =TEXT(A13,"mmmm") -> January | C13: Marketing | D13: Training | E13: East | F13: 18588 | G13: 19889 | H13: Card | I13: TXN100012 | J13: Expense
A14: 2025-01-12 00:00:00 | B14: =TEXT(A14,"mmmm") -> January | C14: Sales | D14: Product Revenue | E14: South | F14: 109116 | G14: 104510 | H14: Bank Transfer | I14: TXN100013 | J14: Income
A15: 2025-01-12 00:00:00 | B15: =TEXT(A15,"mmmm") -> January | C15: Marketing | D15: Product Revenue | E15: South | F15: 130512 | G15: 143211 | H15: Cash | I15: TXN100014 | J15: Income
A16: 2025-01-12 00:00:00 | B16: =TEXT(A16,"mmmm") -> January | C16: Marketing | D16: Product Revenue | E16: West | F16: 147819 | G16: 144515 | H16: UPI | I16: TXN100015 | J16: Income
A17: 2025-01-12 00:00:00 | B17: =TEXT(A17,"mmmm") -> January | C17: Sales | D17: Product Revenue | E17: East | F17: 109358 | G17: 115214 | H17: Card | I17: TXN100016 | J17: Income
A18: 2025-01-20 00:00:00 | B18: =TEXT(A18,"mmmm") -> January | C18: Sales | D18: Service Revenue | E18: East | F18: 70294 | G18: 73422 | H18: Card | I18: TXN100017 | J18: Income
A19: 2025-02-25 00:00:00 | B19: =TEXT(A19,"mmmm") -> February | C19: Operations | D19: Salaries | E19: Central | F19: 56216 | G19: 55820 | H19: Bank Transfer | I19: TXN100018 | J19: Expense
A20: 2025-02-25 00:00:00 | B20: =TEXT(A20,"mmmm") -> February | C20: Finance | D20: Salaries | E20: South | F20: 48752 | G20: 49379 | H20: Bank Transfer | I20: TXN100019 | J20: Expense
A21: 2025-02-25 00:00:00 | B21: =TEXT(A21,"mmmm") -> February | C21: Marketing | D21: Salaries | E21: West | F21: 51572 | G21: 51092 | H21: Bank Transfer | I21: TXN100020 | J21: Expense
... A202: 2025-12-20 00:00:00 | B202: =TEXT(A202,"mmmm") -> December | C202: Sales | D202: Service Revenue | E202: East | F202: 67082 | G202: 66358 | H202: UPI | I202: TXN100201 | J202: Income
